setup.py
operative/__init__.py
operative/settings.py
operative/models/__init__.py
operative/reports/__init__.py
operative/reports/line_item_report.py
operative/test/__init__.py
operative/test/ftp_test.py
operative/test/report_test.py
python_operative.egg-info/PKG-INFO
python_operative.egg-info/SOURCES.txt
python_operative.egg-info/dependency_links.txt
python_operative.egg-info/requires.txt
python_operative.egg-info/top_level.txt