Metadata-Version: 1.0
Name: python-operative
Version: 0.1.1
Summary: A lightweight Python bridge to the Operative FTP flatfile system
Home-page: http://github.com/buzzfeed/python-operative
Author: Jane Kelly & Jeff Revesz
Author-email: jane.kelly@buzzfeed.com
License: UNKNOWN
Keywords: api operative bridge
Platform: UNKNOWN
Classifier: Development Status :: 3 - Alpha
Classifier: Intended Audience :: Developers
